themoviedb/__init__.py
themoviedb/aiotmdb.py
themoviedb/tmdb.py
themoviedb/utils.py
themoviedb/routes_async/__init__.py
themoviedb/routes_async/_base.py
themoviedb/routes_async/authentication.py
themoviedb/routes_async/certifications.py
themoviedb/routes_async/collections.py
themoviedb/routes_async/companies.py
themoviedb/routes_async/credit.py
themoviedb/routes_async/discover.py
themoviedb/routes_async/episode_groups.py
themoviedb/routes_async/episodes.py
themoviedb/routes_async/find.py
themoviedb/routes_async/genres.py
themoviedb/routes_async/guest.py
themoviedb/routes_async/keywords.py
themoviedb/routes_async/movies.py
themoviedb/routes_async/network.py
themoviedb/routes_async/people.py
themoviedb/routes_async/reviews.py
themoviedb/routes_async/search.py
themoviedb/routes_async/seasons.py
themoviedb/routes_async/trending.py
themoviedb/routes_async/tv.py
themoviedb/routes_async/watch_providers.py
themoviedb/routes_sync/__init__.py
themoviedb/routes_sync/_base.py
themoviedb/routes_sync/authentication.py
themoviedb/routes_sync/certifications.py
themoviedb/routes_sync/collections.py
themoviedb/routes_sync/companies.py
themoviedb/routes_sync/credit.py
themoviedb/routes_sync/discover.py
themoviedb/routes_sync/episode_groups.py
themoviedb/routes_sync/episodes.py
themoviedb/routes_sync/find.py
themoviedb/routes_sync/genres.py
themoviedb/routes_sync/guest.py
themoviedb/routes_sync/keywords.py
themoviedb/routes_sync/movies.py
themoviedb/routes_sync/network.py
themoviedb/routes_sync/people.py
themoviedb/routes_sync/reviews.py
themoviedb/routes_sync/search.py
themoviedb/routes_sync/seasons.py
themoviedb/routes_sync/trending.py
themoviedb/routes_sync/tv.py
themoviedb/routes_sync/watch_providers.py
themoviedb/schemas/__init__.py
themoviedb/schemas/_enums.py
themoviedb/schemas/_partial.py
themoviedb/schemas/_result.py
themoviedb/schemas/alternative_names.py
themoviedb/schemas/alternative_titles.py
themoviedb/schemas/authentication.py
themoviedb/schemas/certifications.py
themoviedb-1.0.2.dist-info/LICENSE
themoviedb-1.0.2.dist-info/METADATA
themoviedb-1.0.2.dist-info/WHEEL
themoviedb-1.0.2.dist-info/top_level.txt
themoviedb-1.0.2.dist-info/RECORD
