Metadata-Version: 2.1
Name: themoviedb
Version: 1.0.2
Summary: A modern and easy to use API wrapper for The Movie Database (TMDb) API v3 written in Python
Home-page: https://github.com/leandcesar/themoviedb
Author: Leandro César
Author-email: ccleandroc@gmail.com
License: MIT
Keywords: tmdb,tmdb3,aiotmdb,aiotmdb3,themoviedb,themoviedb3,movie,movies,tv,tv show,tv shows
Platform: UNKNOWN
Classifier: License :: OSI Approved :: MIT License
Classifier: Natural Language :: English
Classifier: Programming Language :: Python
Classifier: Programming Language :: Python :: 3
Classifier: Programming Language :: Python :: 3.8
Classifier: Programming Language :: Python :: 3.9
Classifier: Programming Language :: Python :: 3.10
Classifier: Programming Language :: Python :: 3.11
Requires-Python: >=3.8
License-File: LICENSE
Requires-Dist: aiohttp (>=3.8.4)
Requires-Dist: dacite (>=1.8.0)
Requires-Dist: requests (>=2.31.0)
